cert_normalizer/__init__.py
cert_normalizer/__main__.py
cert_normalizer/normalizer.py
cert_normalizer/py.typed
cert_normalizer-1.0.0.dist-info/METADATA
cert_normalizer-1.0.0.dist-info/WHEEL
cert_normalizer-1.0.0.dist-info/top_level.txt
cert_normalizer-1.0.0.dist-info/RECORD
