Metadata-Version: 2.1
Name: cert-normalizer
Version: 1.0.0
Summary: Нормализатор сертификата в формате base64
Home-page: https://github.com/Gwinkamp/cert-normalizer.git
Author: Gwinkamp
Author-email: Aleksey-Y-Kiryutin@yandex.ru
Keywords: tools
Classifier: Topic :: Utilities
Requires-Python: >=3.10
Requires-Dist: typer >=0.9.0
